agavedb/__init__.py
agavedb/keyval.py
agavedb/uniqueid.py
agavedb-0.4.2.data/data/requirements-travis.txt
agavedb-0.4.2.data/data/requirements.txt
agavedb-0.4.2.dist-info/METADATA
agavedb-0.4.2.dist-info/RECORD
agavedb-0.4.2.dist-info/WHEEL
agavedb-0.4.2.dist-info/top_level.txt
