Metadata-Version: 2.1
Name: agavedb
Version: 0.4.2
Summary: Multiuser-aware key/value store built atop AgaveAPI metadata
Home-page: https://github.com/TACC/agavedb
Author: Matthew W. Vaughn
Author-email: vaughn@tacc.utexas.edu
License: BSD
Platform: UNKNOWN
Classifier: Development Status :: 4 - Beta
Classifier: Intended Audience :: Developers
Classifier: License :: OSI Approved :: BSD License
Classifier: Natural Language :: English
Classifier: Programming Language :: Python
Classifier: Programming Language :: Python :: 2
Classifier: Programming Language :: Python :: 2.7
Classifier: Programming Language :: Python :: 3
Classifier: Programming Language :: Python :: 3.6
Classifier: Operating System :: OS Independent
Classifier: Environment :: Other Environment
Classifier: Topic :: Software Development :: Libraries :: Python Modules
Requires-Dist: attrdict (>=2.0.0)
Requires-Dist: agavepy (>=0.7.0)
Requires-Dist: hashids (>=1.2.0)
